Workbook

Sheet ReadMe
A1: SaaS Finance & Revenue Analytics Model
A2: Excel + Power BI practice project — built to accompany the Power BI dashboard
A4: How this workbook is organized:
A5: 1. Monthly_Actuals - the source-of-truth monthly SaaS metrics (MRR, ARR, movements, Gross Margin, churn, NRR).
A6: 2. Budget_vs_Actual - budget targets vs. actuals, variance $ and %, RAG status.
A7: 3. Revenue_Forecast - FORECAST.LINEAR projection for the next 6 months based on trailing actuals.
A8: 4. KPI_Summary - headline SaaS KPIs (ARR, ACV, Gross Margin %, Churn Rate, NRR) with live formulas.
A10: All figures are synthetic/sample data generated for practice - not real company data.
A11: Every yellow-highlighted cell is a live formula, not a hard-coded value - walk through them before your interview.

Sheet Monthly_Actuals
A1: Month | B1: Active Customers | C1: Total MRR | D1: ARR | E1: New MRR | F1: Expansion MRR | G1: Contraction MRR | H1: Churned MRR | I1: Reactivation MRR | J1: Total COGS | K1: Gross Margin $ | L1: Gross Margin % | M1: Churn Rate % | N1: Net Revenue Retention %
A2: Sep-2024 | B2: 3 | C2: 777.28 | D2: =C2*12 -> 9327.36 | E2: 777.28 | F2: 0 | G2: 0 | H2: 0 | I2: 0 | J2: 217.13 | K2: =C2-J2 -> 560.15 | L2: =K2/C2 -> 0.72065408 | M2: n/a | N2: n/a
A3: Oct-2024 | B3: 9 | C3: 4427.27 | D3: =C3*12 -> 53127.24 | E3: 3649.99 | F3: 0 | G3: 0 | H3: 0 | I3: 0 | J3: 1035.52 | K3: =C3-J3 -> 3391.75 | L3: =K3/C3 -> 0.76610417 | M3: =H3/C2 -> 0 | N3: =(C2+F3+G3-H3)/C2 -> 1
A4: Nov-2024 | B4: 12 | C4: 6803.45 | D4: =C4*12 -> 81641.4 | E4: 2461.34 | F4: 0 | G4: 0 | H4: 85.16 | I4: 0 | J4: 1604.75 | K4: =C4-J4 -> 5198.7 | L4: =K4/C4 -> 0.76412702 | M4: =H4/C3 -> 0.01923533 | N4: =(C3+F4+G4-H4)/C3 -> 0.98076467
A5: Dec-2024 | B5: 15 | C5: 8190.97 | D5: =C5*12 -> 98291.64 | E5: 1224.98 | F5: 162.54 | G5: 0 | H5: 0 | I5: 0 | J5: 2086.51 | K5: =C5-J5 -> 6104.46 | L5: =K5/C5 -> 0.74526704 | M5: =H5/C4 -> 0 | N5: =(C4+F5+G5-H5)/C4 -> 1.0238908
A6: Jan-2025 | B6: 16 | C6: 10121.79 | D6: =C6*12 -> 121461.48 | E6: 2142.38 | F6: 286.9 | G6: -410.04 | H6: 88.42 | I6: 0 | J6: 2638.05 | K6: =C6-J6 -> 7483.74 | L6: =K6/C6 -> 0.73936922 | M6: =H6/C5 -> 0.010794814 | N6: =(C5+F6+G6-H6)/C5 -> 0.97417156
A7: Feb-2025 | B7: 19 | C7: 14631.05 | D7: =C7*12 -> 175572.6 | E7: 4317.8 | F7: 305.53 | G7: 0 | H7: 114.07 | I7: 0 | J7: 3692.69 | K7: =C7-J7 -> 10938.36 | L7: =K7/C7 -> 0.74761278 | M7: =H7/C6 -> 0.011269746 | N7: =(C6+F7+G7-H7)/C6 -> 1.0189156
A8: Mar-2025 | B8: 22 | C8: 17626.61 | D8: =C8*12 -> 211519.32 | E8: 2932.59 | F8: 685.16 | G8: -622.19 | H8: 0 | I8: 0 | J8: 4184.37 | K8: =C8-J8 -> 13442.24 | L8: =K8/C8 -> 0.76261062 | M8: =H8/C7 -> 0 | N8: =(C7+F8+G8-H8)/C7 -> 1.0043039
A9: Apr-2025 | B9: 25 | C9: 20141.11 | D9: =C9*12 -> 241693.32 | E9: 2604.69 | F9: 0 | G9: -90.19 | H9: 0 | I9: 0 | J9: 4627.48 | K9: =C9-J9 -> 15513.63 | L9: =K9/C9 -> 0.77024702 | M9: =H9/C8 -> 0 | N9: =(C8+F9+G9-H9)/C8 -> 0.9948833
A10: May-2025 | B10: 27 | C10: 25369.79 | D10: =C10*12 -> 304437.48 | E10: 5079.72 | F10: 758.68 | G10: 0 | H10: 609.72 | I10: 0 | J10: 6014.62 | K10: =C10-J10 -> 19355.17 | L10: =K10/C10 -> 0.76292196 | M10: =H10/C9 -> 0.030272413 | N10: =(C9+F10+G10-H10)/C9 -> 1.0073958
A11: Jun-2025 | B11: 31 | C11: 28818.52 | D11: =C11*12 -> 345822.24 | E11: 2187.24 | F11: 1292.1 | G11: -30.61 | H11: 0 | I11: 0 | J11: 6537.81 | K11: =C11-J11 -> 22280.71 | L11: =K11/C11 -> 0.77313859 | M11: =H11/C10 -> 0 | N11: =(C10+F11+G11-H11)/C10 -> 1.0497241
A12: Jul-2025 | B12: 33 | C12: 29526.23 | D12: =C12*12 -> 354314.76 | E12: 335.83 | F12: 1045.66 | G12: -97.78 | H12: 576 | I12: 0 | J12: 7278.37 | K12: =C12-J12 -> 22247.86 | L12: =K12/C12 -> 0.75349477 | M12: =H12/C11 -> 0.019987147 | N12: =(C11+F12+G12-H12)/C11 -> 1.0129042
A13: Aug-2025 | B13: 36 | C13: 35240.56 | D13: =C13*12 -> 422886.72 | E13: 6445.76 | F13: 96.02 | G13: 0 | H13: 827.45 | I13: 0 | J13: 7995.66 | K13: =C13-J13 -> 27244.9 | L13: =K13/C13 -> 0.77311201 | M13: =H13/C12 -> 0.028024235 | N13: =(C12+F13+G13-H13)/C12 -> 0.97522779
A14: Sep-2025 | B14: 40 | C14: 37696.85 | D14: =C14*12 -> 452362.2 | E14: 404.86 | F14: 2088.26 | G14: -36.83 | H14: 0 | I14: 0 | J14: 9066.29 | K14: =C14-J14 -> 28630.56 | L14: =K14/C14 -> 0.75949476 | M14: =H14/C13 -> 0 | N14: =(C13+F14+G14-H14)/C13 -> 1.0582122
... A25: Aug-2026 | B25: 78 | C25: 58573.69 | D25: =C25*12 -> 702884.28 | E25: 1005.86 | F25: 2782.65 | G25: -80.15 | H25: 296.54 | I25: 98.92 | J25: 14510.41 | K25: =C25-J25 -> 44063.28 | L25: =K25/C25 -> 0.75227086 | M25: =H25/C24 -> 0.0053854724 | N25: =(C24+F25+G25-H25)/C24 -> 1.0436947

Sheet Budget_vs_Actual
A1: Month | B1: Budget Revenue | C1: Actual Revenue | D1: Variance $ | E1: Variance % | F1: Status
A2: Sep-2024 | B2: 804.95 | C2: =Monthly_Actuals!C2 -> 777.28 | D2: =C2-B2 -> -27.67 | E2: =D2/B2 -> -0.034374806 | F2: =IF(D2>=0,"Above Budget","Below Budget") -> Below Budget
A3: Oct-2024 | B3: 3356.91 | C3: =Monthly_Actuals!C3 -> 4427.27 | D3: =C3-B3 -> 1070.36 | E3: =D3/B3 -> 0.31885275 | F3: =IF(D3>=0,"Above Budget","Below Budget") -> Above Budget
A4: Nov-2024 | B4: 6095.36 | C4: =Monthly_Actuals!C4 -> 6803.45 | D4: =C4-B4 -> 708.09 | E4: =D4/B4 -> 0.11616869 | F4: =IF(D4>=0,"Above Budget","Below Budget") -> Above Budget
A5: Dec-2024 | B5: 8896.77 | C5: =Monthly_Actuals!C5 -> 8190.97 | D5: =C5-B5 -> -705.8 | E5: =D5/B5 -> -0.079332162 | F5: =IF(D5>=0,"Above Budget","Below Budget") -> Below Budget
A6: Jan-2025 | B6: 11060.37 | C6: =Monthly_Actuals!C6 -> 10121.79 | D6: =C6-B6 -> -938.58 | E6: =D6/B6 -> -0.084859729 | F6: =IF(D6>=0,"Above Budget","Below Budget") -> Below Budget
A7: Feb-2025 | B7: 14088.64 | C7: =Monthly_Actuals!C7 -> 14631.05 | D7: =C7-B7 -> 542.41 | E7: =D7/B7 -> 0.038499813 | F7: =IF(D7>=0,"Above Budget","Below Budget") -> Above Budget
A8: Mar-2025 | B8: 16753.58 | C8: =Monthly_Actuals!C8 -> 17626.61 | D8: =C8-B8 -> 873.03 | E8: =D8/B8 -> 0.052110056 | F8: =IF(D8>=0,"Above Budget","Below Budget") -> Above Budget
A9: Apr-2025 | B9: 18057.75 | C9: =Monthly_Actuals!C9 -> 20141.11 | D9: =C9-B9 -> 2083.36 | E9: =D9/B9 -> 0.11537207 | F9: =IF(D9>=0,"Above Budget","Below Budget") -> Above Budget
A10: May-2025 | B10: 22986.68 | C10: =Monthly_Actuals!C10 -> 25369.79 | D10: =C10-B10 -> 2383.11 | E10: =D10/B10 -> 0.10367352 | F10: =IF(D10>=0,"Above Budget","Below Budget") -> Above Budget
A11: Jun-2025 | B11: 25348.88 | C11: =Monthly_Actuals!C11 -> 28818.52 | D11: =C11-B11 -> 3469.64 | E11: =D11/B11 -> 0.13687548 | F11: =IF(D11>=0,"Above Budget","Below Budget") -> Above Budget
A12: Jul-2025 | B12: 26734.99 | C12: =Monthly_Actuals!C12 -> 29526.23 | D12: =C12-B12 -> 2791.24 | E12: =D12/B12 -> 0.104404 | F12: =IF(D12>=0,"Above Budget","Below Budget") -> Above Budget
A13: Aug-2025 | B13: 29881.23 | C13: =Monthly_Actuals!C13 -> 35240.56 | D13: =C13-B13 -> 5359.33 | E13: =D13/B13 -> 0.1793544 | F13: =IF(D13>=0,"Above Budget","Below Budget") -> Above Budget
... A25: Aug-2026 | B25: 67127.36 | C25: =Monthly_Actuals!C25 -> 58573.69 | D25: =C25-B25 -> -8553.67 | E25: =D25/B25 -> -0.1274245 | F25: =IF(D25>=0,"Above Budget","Below Budget") -> Below Budget
A27: Trailing 3-Month Avg Variance % | B27: =AVERAGE(E24:E25) -> -0.093098639

Sheet Revenue_Forecast
A1: Month | B1: Actual MRR | C1: Forecast MRR | E1: MonthIndex
A2: Sep-2024 | B2: 777.28 | E2: 1
A3: Oct-2024 | B3: 4427.27 | E3: 2
A4: Nov-2024 | B4: 6803.45 | E4: 3
A5: Dec-2024 | B5: 8190.97 | E5: 4
A6: Jan-2025 | B6: 10121.79 | E6: 5
A7: Feb-2025 | B7: 14631.05 | E7: 6
A8: Mar-2025 | B8: 17626.61 | E8: 7
A9: Apr-2025 | B9: 20141.11 | E9: 8
A10: May-2025 | B10: 25369.79 | E10: 9
A11: Jun-2025 | B11: 28818.52 | E11: 10
A12: Jul-2025 | B12: 29526.23 | E12: 11
A13: Aug-2025 | B13: 35240.56 | E13: 12
... A24: Jul-2026 | B24: 55062.95 | E24: 23
A25: Aug-2026 | B25: 58573.69 | C25: =B25 -> 58573.69 | E25: 24
A26: Sep-2026 | C26: =_xlfn.FORECAST.LINEAR(E26,$B$2:$B$25,$E$2:$E$25) -> 62378.275 | E26: 25
A27: Oct-2026 | C27: =_xlfn.FORECAST.LINEAR(E27,$B$2:$B$25,$E$2:$E$25) -> 64843.918 | E27: 26
A28: Nov-2026 | C28: =_xlfn.FORECAST.LINEAR(E28,$B$2:$B$25,$E$2:$E$25) -> 67309.561 | E28: 27
A29: Dec-2026 | C29: =_xlfn.FORECAST.LINEAR(E29,$B$2:$B$25,$E$2:$E$25) -> 69775.204 | E29: 28
A30: Jan-2027 | C30: =_xlfn.FORECAST.LINEAR(E30,$B$2:$B$25,$E$2:$E$25) -> 72240.848 | E30: 29
A31: Feb-2027 | C31: =_xlfn.FORECAST.LINEAR(E31,$B$2:$B$25,$E$2:$E$25) -> 74706.491 | E31: 30

Sheet KPI_Summary
A1: SaaS KPI Summary — Latest Month
A3: Metric | B3: Value | C3: Definition
A4: ARR (Annual Recurring Revenue) | B4: =Monthly_Actuals!D25 -> 702884.28 | C4: Ending MRR x 12. Headline SaaS scale metric.
A5: ACV (Average Contract Value) | B5: =Monthly_Actuals!D25/Monthly_Actuals!B25 -> 9011.3369 | C5: ARR divided by active customer count — average annual value per account.
A6: MRR (Monthly Recurring Revenue) | B6: =Monthly_Actuals!C25 -> 58573.69 | C6: Predictable monthly subscription revenue for the latest month.
A7: Gross Margin % | B7: =Monthly_Actuals!L25 -> 0.75227086 | C7: (MRR - COGS) / MRR — profitability of the recurring revenue base.
A8: Monthly Churn Rate % | B8: =Monthly_Actuals!M25 -> 0.0053854724 | C8: Churned MRR / prior month Total MRR.
A9: Net Revenue Retention % | B9: =Monthly_Actuals!N25 -> 1.0436947 | C9: (Prior MRR + Expansion + Contraction - Churn) / Prior MRR. >100% = expansion outpaces churn.
A10: Trailing 3-Month Avg Budget Variance % | B10: =Budget_vs_Actual!B27 -> -0.093098639 | C10: How actual revenue has tracked vs. budget over the last 3 months.
A11: 6-Month Forecast MRR (next period) | B11: =Revenue_Forecast!C26 -> 62378.275 | C11: FORECAST.LINEAR trend projection for the month after the latest actual.
